[{
	"month" : "December",
	"completed" : true,
	"awarded" : [{
			"name" : "Eriks Harchevs",
			"source" : ""
		}, {
			"name" : "Teodors Zeltiņš",
			"source" : ""
		}, {
			"name" : "Jurijs Saveljevs",
			"source" : ""
		}],
	"details" : "https://github.com/latcraft/cloudopoly-search"
}, {
	"month" : "January",
	"completed" : true,
	"awarded" : [{
			"name" : "Vadims Yagodins",
			"source" : ""
		}, {
			"name" : "Vlad Moiseyenko",
			"source" : ""
		}, {
			"name" : "Sandris Artemjevs",
			"source" : ""
		}],
	"details" : "https://github.com/latcraft/cloudopoly-pics"
}, {
	"month" : "February",
	"cancelled" : true,
	"details" : "https://github.com/latcraft/cloudopoly-docker/"
}]